zcomm/__init__.py
zcomm/services.py
zcomm-0.0.2.dist-info/METADATA
zcomm-0.0.2.dist-info/WHEEL
zcomm-0.0.2.dist-info/top_level.txt
zcomm-0.0.2.dist-info/RECORD
